{
  "world_id": "world",
  "checksum": "fnv1a_4d2d72b9",
  "burg_id": 202,
  "name": "Mangis",
  "state_id": -1,
  "province_id": "unknown",
  "tags": [],
  "size_hint": "small",
  "economy_roles": [
    "river-trade",
    "fishing and fish-curing",
    "ritual-labour services",
    "timber milling"
  ],
  "factions_local": [
    "Harbormaster's Enclave",
    "Shrine of River-Ancestors",
    "Boatmen's Cooperative",
    "Night-Market Crews"
  ],
  "problems": [
    "reagent-scarcity for rituals",
    "banditry along the river",
    "harbor corruption"
  ],
  "religion_presence": [
    "Sea-Tide Animisms",
    "Ancestor-Remembrance Cults"
  ],
  "culture_notes": [
    "Riveric Dialect dominant",
    "Ancestor-offerings performed at landings",
    "Diet: smoked and salted fish staples",
    "Seasonal boat-festivals with talismanic rites"
  ],
  "quest_hook_slots": [
    "smuggling",
    "ritual-reagent shortage",
    "river-monster sightings"
  ],
  "constraints": [
    "no instant resurrection or true life-replacement magics",
    "ritual magic consumes scarce imported reagents; combustion industry limited"
  ],
  "notes": [
    "Near-medieval to early-industrial tech with local ritual magic",
    "Situated at a navigable river mouth; political state ties unclear"
  ],
  "generated_at": "2025-09-09T05:28:15.100Z"
}