{
  "world_id": "world",
  "checksum": "fnv1a_bef8f2f6",
  "burg_id": 29,
  "name": "Gatford",
  "state_id": -1,
  "province_id": "unknown",
  "tags": [],
  "size_hint": "small",
  "economy_roles": [
    "river-crossing market",
    "ferry tolls",
    "grain trade",
    "boat repair"
  ],
  "factions_local": [
    "tollkeepers' guild",
    "ferrymen's union",
    "merchant traders",
    "temple caretakers"
  ],
  "problems": [
    "seasonal flooding",
    "bandit raids",
    "reagent scarcity"
  ],
  "religion_presence": [
    "Ancestor-Remembrance Cults",
    "Sea-Tide Animisms",
    "Merchant Brotherhood Liturgies"
  ],
  "culture_notes": [
    "Riveric Dialect dominant",
    "smoked fish and barley gruel cuisine",
    "blessing rites performed at the ford",
    "strong boatwright craft tradition"
  ],
  "quest_hook_slots": [
    "smuggling",
    "river-monster",
    "toll corruption"
  ],
  "constraints": [
    "rituals consume scarce imported reagents",
    "limited combustion industry; no high-pressure steam megatechs",
    "long-range mind influence banned"
  ],
  "notes": [
    "ford closes in high water",
    "harbor shallow; large ships anchor offshore"
  ],
  "generated_at": "2025-09-09T05:33:56.911Z"
}