{
  "world_id": "world",
  "checksum": "fnv1a_6d3ca2c4",
  "burg_id": 315,
  "name": "Brybgar",
  "state_id": -1,
  "province_id": "unknown",
  "tags": [],
  "size_hint": "outpost",
  "economy_roles": [
    "river ferry",
    "timber export",
    "smoked-fish market"
  ],
  "factions_local": [
    "Ferrywrights' Guild",
    "River Watch militia",
    "Temple of Tide elders",
    "Smuggler network"
  ],
  "problems": [
    "seasonal flooding",
    "bandit raids",
    "reagent scarcity"
  ],
  "religion_presence": [
    "Sea-Tide Animisms",
    "Ancestor-Remembrance Cults"
  ],
  "culture_notes": [
    "Riveric dialect dominant",
    "rituals tied to tides and harvest",
    "diet centered on smoked/salted fish",
    "transient, work-season population"
  ],
  "quest_hook_slots": [
    "smuggling",
    "levee failure",
    "missing ferry crew"
  ],
  "constraints": [
    "ritual magic consumes scarce imported reagents",
    "long-range mind influence is rare and institutionally banned",
    "combustion industry limited; no high-pressure steam megatechs"
  ],
  "notes": [
    "monthly reagent barge connects to coastal port",
    "located at a strategic river ford"
  ],
  "generated_at": "2025-09-09T05:35:33.051Z"
}